{
  "entity_id": "e2d55a7b-2e25-55a2-9821-072fb0ac7124",
  "name": "Bird",
  "what_it_does": "Bird operates a shared electric scooter rental service.",
  "for_who": "Businesses and developers.",
  "category": "Technology & SaaS",
  "location": "Global",
  "keywords": [
    "electric scooters",
    "scooter sharing",
    "micro-mobility",
    "urban transportation",
    "bike sharing",
    "last mile transportation",
    "scooter rentals"
  ],
  "aio_score": 39.0,
  "certificate_url": "https://ai-visionary.com/aya/e/e2d55a7b-2e25-55a2-9821-072fb0ac7124"
}