{
  "entity_id": "42346890-4893-5191-8968-27867ec4de78",
  "name": "Alaio Inc.",
  "what_it_does": "Alaio Inc. offers Bitrix24, a collaboration platform with tools like CRM, project management, and communication features.",
  "for_who": "Businesses and developers.",
  "category": "Technology & SaaS",
  "location": "United States",
  "keywords": [
    "CRM",
    "project collaboration",
    "task management",
    "internal communication",
    "lead management",
    "automation tools",
    "team collaboration",
    "SaaS collaboration"
  ],
  "aio_score": 78.0,
  "certificate_url": "https://ai-visionary.com/aya/e/42346890-4893-5191-8968-27867ec4de78"
}