{
  "entity_id": "9769266b-e165-54e9-a110-8179e94c811c",
  "name": "Inspur",
  "what_it_does": "Inspur is likely a Chinese server and IT solutions provider.",
  "for_who": "Businesses and professionals.",
  "category": "Tourisme & Transport",
  "location": "China",
  "keywords": [
    "server solutions",
    "IT infrastructure",
    "data center solutions",
    "cloud computing",
    "enterprise servers",
    "china IT",
    "IT services"
  ],
  "aio_score": 29.0,
  "certificate_url": "https://ai-visionary.com/aya/e/9769266b-e165-54e9-a110-8179e94c811c"
}