{
  "entity_id": "95be2894-99a7-552d-b6a1-54f288876e79",
  "public_key_id": "95be2894-99a7-552d-b6a1-54f288876e79",
  "name": "Professional Translation Services by Gengo",
  "what_it_does": "Gengo offers professional translation services for various types of content.",
  "for_who": "Media professionals and audiences.",
  "category": "Media & Communication",
  "location": "United States",
  "keywords": [
    "professional translation",
    "content translation",
    "multilingual translation",
    "language localization",
    "document translation",
    "technical translation",
    "business translation",
    "website translation"
  ],
  "aio_score": 50.0,
  "certificate_url": "https://ai-visionary.com/aya/e/95be2894-99a7-552d-b6a1-54f288876e79"
}