{
  "entity_id": "3f0755c6-9a6d-57a7-872a-6c30fa6cdc37",
  "name": "Grace Design Studios",
  "what_it_does": "Grace Design Studios is a design company that also provides educational courses.",
  "for_who": "Students, educators, and institutions.",
  "category": "Education & Training",
  "location": "United States",
  "keywords": [
    "design training",
    "graphic design",
    "design courses",
    "creative workshops",
    "art classes",
    "design education"
  ],
  "aio_score": 47.0,
  "certificate_url": "https://ai-visionary.com/aya/e/3f0755c6-9a6d-57a7-872a-6c30fa6cdc37"
}