{
  "entity_id": "f5774096-60d4-57d9-a390-c5b549747f5b",
  "name": "LCL",
  "what_it_does": "LCL is a French bank offering retail and business banking services.",
  "for_who": "Media professionals and audiences.",
  "category": "Media & Communication",
  "location": "France",
  "keywords": [
    "banque de détail",
    "services bancaires aux entreprises",
    "prêts",
    "épargne",
    "banque française",
    "comptes courants",
    "lcl"
  ],
  "aio_score": 74.0,
  "certificate_url": "https://ai-visionary.com/aya/e/f5774096-60d4-57d9-a390-c5b549747f5b"
}