{
  "entity_id": "4df22dc6-54d1-5e08-a4b2-c46e087a5e8a",
  "public_key_id": "4df22dc6-54d1-5e08-a4b2-c46e087a5e8a",
  "name": "Leidos. Outsmart. Outdo.",
  "what_it_does": "Leidos provides technology, engineering, and science solutions and services to government, defense, aviation, and commercial customers.",
  "for_who": "Businesses and developers.",
  "category": "Technology & SaaS",
  "location": "Australia",
  "keywords": [
    "Government Solutions",
    "Defense Technology",
    "Aviation Engineering",
    "Science Applications",
    "Federal IT",
    "Aerospace Systems",
    "National Security",
    "Engineering Solutions"
  ],
  "aio_score": 50.0,
  "certificate_url": "https://ai-visionary.com/aya/e/4df22dc6-54d1-5e08-a4b2-c46e087a5e8a"
}