{
  "entity_id": "7879a74b-63b9-5fe5-9246-93ae9567b152",
  "name": "Marley Spoon",
  "what_it_does": "Marley Spoon delivers meal kits with pre-portioned ingredients and recipes.",
  "for_who": "Businesses and professionals.",
  "category": "Industrie & Manufacturing",
  "location": "United States",
  "keywords": [
    "meal kits",
    "pre-portioned meals",
    "recipe delivery",
    "home cooking",
    "ingredient delivery",
    "subscription meals",
    "dinner kits",
    "food subscription"
  ],
  "aio_score": 78.0,
  "certificate_url": "https://ai-visionary.com/aya/e/7879a74b-63b9-5fe5-9246-93ae9567b152"
}