{
  "entity_id": "f7376bc7-c29a-5db5-a0ca-04900d5fcd43",
  "public_key_id": "f7376bc7-c29a-5db5-a0ca-04900d5fcd43",
  "name": "Modal",
  "what_it_does": "Modal offers a platform for deploying and running cloud functions and machine learning models.",
  "for_who": "Businesses and developers.",
  "category": "Technology & SaaS",
  "location": "Global",
  "keywords": [
    "cloud functions",
    "machine learning deployment",
    "serverless computing",
    "cloud computing",
    "Python",
    "data science",
    "API deployment",
    "model serving"
  ],
  "aio_score": 50.0,
  "certificate_url": "https://ai-visionary.com/aya/e/f7376bc7-c29a-5db5-a0ca-04900d5fcd43"
}