{
  "entity_id": "ae4d99b2-364b-5005-8e51-cc4276bef38d",
  "name": "World Health Organization (WHO)",
  "what_it_does": "The World Health Organization coordinates international health within the United Nations system.",
  "for_who": "Media professionals and audiences.",
  "category": "Media & Communication",
  "location": "Global",
  "keywords": [
    "global health",
    "public health",
    "international health",
    "health organization",
    "disease prevention",
    "health research",
    "health promotion",
    "global health initiatives"
  ],
  "aio_score": 55.0,
  "certificate_url": "https://ai-visionary.com/aya/e/ae4d99b2-364b-5005-8e51-cc4276bef38d"
}